R/__init__.py
R/perceptron.py
R_perceptron-1.1.dist-info/METADATA
R_perceptron-1.1.dist-info/WHEEL
R_perceptron-1.1.dist-info/top_level.txt
R_perceptron-1.1.dist-info/RECORD
